{
  "tasks": [
    {
      "title": "Learning reactjs",
      "description": "Redux form",
      "status": 2,
      "id": 1
    },
    {
      "title": "Learning SASS",
      "status": 1,
      "id": 2
    },
    {
      "title": "Learning Java",
      "description": "OOP",
      "status": 0,
      "id": 3
    },
    {
      "id": 4
    },
    {
      "id": 5
    },
    {
      "id": 6
    },
    {
      "id": 7
    },
    {
      "id": 8
    },
    {
      "title": "Learning English",
      "status": 0,
      "id": 9
    },
    {
      "title": "Learning Ruby",
      "description": "BACKEND",
      "status": 0,
      "id": 10
    },
    {
      "title": "Learning Nodejs",
      "description": "MVC",
      "status": 0,
      "id": 11
    },
    {
      "title": "Learning Music",
      "description": null,
      "status": 1,
      "id": 12
    }
  ]
}